{
  "title": "AI 快讯 · Twitter",
  "date": "2025-09-21T15:30:06Z",
  "topics": [
    {
      "topic_id": "cluster--1",
      "headline": "AI模型进展与行业动态",
      "bullets": [
        {
          "text": "GoogleAI的Gemini 2.5 Deep Think模型在某项竞赛中达到金牌水平表现。",
          "url": "https://x.com/GoogleAI/status/1969122206744789076"
        },
        {
          "text": "IBM发布了更新的SmolDocling，一个258M参数的VLM，具备OCR能力并采用Apache 2.0许可。",
          "url": "https://x.com/huggingface/status/1969133250804060237"
        },
        {
          "text": "小米推出了MiMo-Audio开放音频模型。",
          "url": "https://x.com/huggingface/status/1969133330927944084"
        },
        {
          "text": "中国超大规模厂商预计到2025年，每日Token消耗将从50万亿增至400-500万亿。",
          "url": "https://x.com/EMostaque/status/1969737509904273887"
        }
      ]
    },
    {
      "topic_id": "cluster-2",
      "headline": "AI生态系统与模型创新",
      "bullets": [
        {
          "text": "Hugging Face平台公共数据集数量突破50万，平均每60秒新增一个数据集。",
          "url": "https://x.com/huggingface/status/1969133448922005727"
        },
        {
          "text": "Moondream 3预览版发布，这是一个9B参数、2B活跃MoE的视觉语言模型。",
          "url": "https://x.com/EMostaque/status/1969097237029396693"
        },
        {
          "text": "LumaLabsAI推出RAY3模型，能够原生生成HDR视频。",
          "url": "https://x.com/EMostaque/status/1969104823355142478"
        },
        {
          "text": "NVIDIA指出，Agentic AI和生成式AI正在重塑英国的工业、创造和连接方式。",
          "url": "https://x.com/NVIDIAAI/status/1969106762851635259"
        }
      ]
    },
    {
      "topic_id": "cluster-1",
      "headline": "PyTorchCon大会预告",
      "bullets": [
        {
          "text": "Qualcomm工程高级副总裁J. Gehlhaar将在PyTorchCon大会上发表主题演讲。",
          "url": "https://x.com/PyTorch/status/1969054125917651396"
        }
      ]
    },
    {
      "topic_id": "cluster-0",
      "headline": "新的实验追踪库Trackio发布",
      "bullets": [
        {
          "text": "Trackio是一个新的免费实验追踪库，其语法与wandb相同，可作为便捷的替代品。",
          "url": "https://x.com/huggingface/status/1969054496866103424"
        },
        {
          "text": "该库被宣传为轻量、免费且易于使用，并有相关讨论视频。",
          "url": "https://x.com/huggingface/status/1969054489882571080"
        }
      ]
    }
  ]
}